setup.py
django_git_info/__init__.py
django_git_info/gitint.py
django_git_info/tests.py
django_git_info/views.py
django_git_info.egg-info/PKG-INFO
django_git_info.egg-info/SOURCES.txt
django_git_info.egg-info/dependency_links.txt
django_git_info.egg-info/not-zip-safe
django_git_info.egg-info/requires.txt
django_git_info.egg-info/top_level.txt
django_git_info/management/__init__.py
django_git_info/management/commands/__init__.py
django_git_info/management/commands/get_git_info.py
django_git_info/migrations/__init__.py
django_git_info/templatetags/__init__.py
django_git_info/templatetags/django_git_info_tags.py